[
  {
    "line": 2,
    "elements": [
      {
        "before": [
          {
            "result": {
              "duration": 2901040200,
              "status": "passed"
            },
            "match": {
              "location": "Hooks.setUp()"
            }
          }
        ],
        "line": 5,
        "name": "User should select Online Slots option successfully",
        "description": "",
        "id": "online-slots;user-should-select-online-slots-option-successfully",
        "after": [
          {
            "result": {
              "duration": 666840500,
              "status": "passed"
            },
            "match": {
              "location": "Hooks.tearDown(Scenario)"
            }
          }
        ],
        "type": "scenario",
        "keyword": "Scenario",
        "steps": [
          {
            "result": {
              "duration": 80313700,
              "status": "passed"
            },
            "line": 6,
            "name": "I am on homepage",
            "match": {
              "location": "MyStepdefs.iAmOnHomepage()"
            },
            "keyword": "Given "
          },
          {
            "result": {
              "duration": 866724400,
              "status": "passed"
            },
            "line": 7,
            "name": "I click on Online Slots link",
            "match": {
              "location": "MyStepdefs.iClickOnOnlineSlotsLink()"
            },
            "keyword": "When "
          },
          {
            "result": {
              "duration": 282488400,
              "status": "passed"
            },
            "line": 8,
            "name": "I should navigate to Online Slots page successfully",
            "match": {
              "location": "MyStepdefs.iShouldNavigateToOnlineSlotsPageSuccessfully()"
            },
            "keyword": "Then "
          }
        ]
      }
    ],
    "name": "Online Slots",
    "description": "As user I want to select Online Slots option",
    "id": "online-slots",
    "keyword": "Feature",
    "uri": "homepage/homepage.feature",
    "tags": [
      {
        "line": 1,
        "name": "@regression"
      }
    ]
  }
]